py_ballisticcalc_exts/.gitignore
py_ballisticcalc_exts/__init__.py
py_ballisticcalc_exts/_test_engine.cpython-314t-arm-linux-musleabihf.so
py_ballisticcalc_exts/_test_engine.pyx
py_ballisticcalc_exts/_test_helpers.cpython-314t-arm-linux-musleabihf.so
py_ballisticcalc_exts/_test_helpers.pyx
py_ballisticcalc_exts/base_engine.cpython-314t-arm-linux-musleabihf.so
py_ballisticcalc_exts/base_engine.pxd
py_ballisticcalc_exts/base_engine.pyi
py_ballisticcalc_exts/base_engine.pyx
py_ballisticcalc_exts/base_types.pxd
py_ballisticcalc_exts/bind.cpython-314t-arm-linux-musleabihf.so
py_ballisticcalc_exts/bind.pxd
py_ballisticcalc_exts/bind.pyx
py_ballisticcalc_exts/euler_engine.cpython-314t-arm-linux-musleabihf.so
py_ballisticcalc_exts/euler_engine.pxd
py_ballisticcalc_exts/euler_engine.pyi
py_ballisticcalc_exts/euler_engine.pyx
py_ballisticcalc_exts/exceptions.pxd
py_ballisticcalc_exts/interp.pxd
py_ballisticcalc_exts/py.typed
py_ballisticcalc_exts/rk4_engine.cpython-314t-arm-linux-musleabihf.so
py_ballisticcalc_exts/rk4_engine.pxd
py_ballisticcalc_exts/rk4_engine.pyi
py_ballisticcalc_exts/rk4_engine.pyx
py_ballisticcalc_exts/traj_data.cpython-314t-arm-linux-musleabihf.so
py_ballisticcalc_exts/traj_data.pxd
py_ballisticcalc_exts/traj_data.pyi
py_ballisticcalc_exts/traj_data.pyx
py_ballisticcalc_exts/v3d.pxd
py_ballisticcalc_exts/include/bclibc.hpp
py_ballisticcalc_exts/include/bclibc/base_types.hpp
py_ballisticcalc_exts/include/bclibc/engine.hpp
py_ballisticcalc_exts/include/bclibc/euler.hpp
py_ballisticcalc_exts/include/bclibc/exceptions.hpp
py_ballisticcalc_exts/include/bclibc/interp.hpp
py_ballisticcalc_exts/include/bclibc/log.hpp
py_ballisticcalc_exts/include/bclibc/py_bind.hpp
py_ballisticcalc_exts/include/bclibc/rk4.hpp
py_ballisticcalc_exts/include/bclibc/scope_guard.hpp
py_ballisticcalc_exts/include/bclibc/traj_data.hpp
py_ballisticcalc_exts/include/bclibc/traj_filter.hpp
py_ballisticcalc_exts/include/bclibc/v3d.hpp
py_ballisticcalc_exts-2.2.8.dist-info/METADATA
py_ballisticcalc_exts-2.2.8.dist-info/WHEEL
py_ballisticcalc_exts-2.2.8.dist-info/entry_points.txt
py_ballisticcalc_exts-2.2.8.dist-info/top_level.txt
py_ballisticcalc_exts-2.2.8.dist-info/RECORD
py_ballisticcalc_exts-2.2.8.dist-info/licenses/LICENSE
py_ballisticcalc_exts-2.2.8.dist-info/sboms/auditwheel.cdx.json
