Metadata-Version: 2.4
Name: py_ballisticcalc.exts
Version: 2.2.8
Summary: LGPL library for small arms ballistic calculations (Python 3)
Author-email: o-murphy <thehelixpg@gmail.com>, dbookstaber <bookstaber@gmail.com>
Project-URL: Homepage, https://github.com/o-murphy/py-ballisticcalc
Project-URL: Bug Reports, https://github.com/o-murphy/py-ballisticcalc/issues
Project-URL: Source, https://github.com/o-murphy/py-ballisticcalc
Keywords: py_ballisticcalc,ballistics,Cython,ballistic calculator,python,python3
Classifier: Intended Audience :: Developers
Classifier: Natural Language :: English
Classifier: Programming Language :: Python
Classifier: Topic :: Software Development :: Libraries :: Python Modules
Classifier: Programming Language :: Python :: 3
Classifier: Programming Language :: Python :: 3 :: Only
Classifier: Programming Language :: Python :: 3.10
Classifier: Programming Language :: Python :: 3.11
Classifier: Programming Language :: Python :: 3.12
Classifier: Programming Language :: Python :: 3.13
Classifier: Programming Language :: Python :: 3.14
Classifier: Operating System :: OS Independent
Classifier: Programming Language :: Python :: Implementation :: CPython
Requires-Python: >=3.10
License-File: LICENSE
Provides-Extra: dev
Requires-Dist: cython>=3.1.4; extra == "dev"
Requires-Dist: cibuildwheel; extra == "dev"
Requires-Dist: setuptools; extra == "dev"
Dynamic: license-file
